.gitignore
.project
.pydevproject
CHANGELOG.rst
CMakeCache.txt
CMakeLists.txt
CTestConfiguration.ini
CTestCustom.cmake
CTestTestfile.cmake
LICENSE
Makefile
README.md
cmake_install.cmake
index.html
install_manifest.txt
package.xml
pom.xml
rosdoc.yaml
setup.py
.catkin_tools/CATKIN_IGNORE
.catkin_tools/README
.catkin_tools/VERSION
.catkin_tools/profiles/default/build.yaml
.cmake/api/v1/reply/index-2022-10-30T21-27-12-0820.json
.github/workflows/docker-image.yml
.github/workflows/docker-publish.yml
.github/workflows/maven-publish.yml
.github/workflows/maven.yml
.github/workflows/pages.yml
CMakeFiles/CMakeError.log
CMakeFiles/CMakeOutput.log
CMakeFiles/CMakeRuleHashes.txt
CMakeFiles/Makefile2
CMakeFiles/TargetDirectories.txt
CMakeFiles/cmake.check_cache
CMakeFiles/progress.marks
CMakeFiles/3.16.3/CMakeCCompiler.cmake
CMakeFiles/3.16.3/CMakeCXXCompiler.cmake
CMakeFiles/3.16.3/CMakeDetermineCompilerABI_C.bin
CMakeFiles/3.16.3/CMakeDetermineCompilerABI_CXX.bin
CMakeFiles/3.16.3/CMakeSystem.cmake
CMakeFiles/3.16.3/CompilerIdC/CMakeCCompilerId.c
CMakeFiles/3.16.3/CompilerIdC/a.out
CMakeFiles/3.16.3/CompilerIdCXX/CMakeCXXCompilerId.cpp
CMakeFiles/3.16.3/CompilerIdCXX/a.out
CMakeFiles/_catkin_empty_exported_target.dir/DependInfo.cmake
CMakeFiles/_catkin_empty_exported_target.dir/build.make
CMakeFiles/_catkin_empty_exported_target.dir/cmake_clean.cmake
CMakeFiles/_catkin_empty_exported_target.dir/progress.make
CMakeFiles/clean_test_results.dir/DependInfo.cmake
CMakeFiles/clean_test_results.dir/build.make
CMakeFiles/clean_test_results.dir/cmake_clean.cmake
CMakeFiles/clean_test_results.dir/progress.make
CMakeFiles/download_extra_data.dir/DependInfo.cmake
CMakeFiles/download_extra_data.dir/build.make
CMakeFiles/download_extra_data.dir/cmake_clean.cmake
CMakeFiles/download_extra_data.dir/progress.make
CMakeFiles/doxygen.dir/DependInfo.cmake
CMakeFiles/doxygen.dir/build.make
CMakeFiles/doxygen.dir/cmake_clean.cmake
CMakeFiles/doxygen.dir/progress.make
src/mobile_message_service_generator.egg-info/PKG-INFO
src/mobile_message_service_generator.egg-info/SOURCES.txt
src/mobile_message_service_generator.egg-info/dependency_links.txt
src/mobile_message_service_generator.egg-info/requires.txt
src/mobile_message_service_generator.egg-info/top_level.txt
