Metadata-Version: 2.1
Name: mobile-message-service-generator
Version: 0.4.3
Summary: ROS Mobile Message Service Generator
Author: Ronaldson Bellande
Author-email: ronaldsonbellande@gmail.com
Project-URL: Home, https://github.com/application-ui-ux/mobile_message_service_generator
Project-URL: Homepage, https://github.com/application-ui-ux/mobile_message_service_generator
Project-URL: documentation, https://github.com/application-ui-ux/mobile_message_service_generator
Project-URL: repository, https://github.com/application-ui-ux/mobile_message_service_generator
Keywords: package,setuptools
Classifier: License :: OSI Approved :: Apache Software License
Classifier: Programming Language :: Python
Requires-Python: >=3.0
Provides-Extra: dev
License-File: LICENSE
